LICENSE.md
MANIFEST.in
README.md
setup.py
PillowImage/__init__.py
PillowImage/_version.py
PillowImage/pillow.py
PillowImage/utils.py
PillowImage.egg-info/PKG-INFO
PillowImage.egg-info/SOURCES.txt
PillowImage.egg-info/dependency_links.txt
PillowImage.egg-info/requires.txt
PillowImage.egg-info/top_level.txt
PillowImage/font/Vera.ttf
PillowImage/font/__init__.py
PillowImage/font/register.py
tests/__init__.py
tests/test_PillowImage_jpeg.py
tests/test_PillowImage_png.py
tests/test_PillowImage_utils.py