Metadata-Version: 2.1
Name: PillowImage
Version: 1.2.0
Summary: Pillow wrapper for quick image alterations.
Home-page: https://github.com/sfneal/PillowImage
Author: Stephen Neal
Author-email: stephen@stephenneal.net
License: MIT
Requires-Python: >=3.6
License-File: LICENSE.md
